jax_vocos/__init__.py
jax_vocos/convert.py
jax_vocos/infer.py
jax_vocos/modeling_flax_pytorch_utils.py
jax_vocos/models.py
jax_vocos/util.py
jax_vocos-0.0.10.dist-info/METADATA
jax_vocos-0.0.10.dist-info/WHEEL
jax_vocos-0.0.10.dist-info/top_level.txt
jax_vocos-0.0.10.dist-info/RECORD
