Metadata-Version: 2.4
Name: jax-vocos
Version: 0.0.10
Summary: JAX Implementation Vocos
Author-email: flyingblackshark <aliu2000@outlook.com>
Project-URL: Homepage, https://github.com/flyingblackshark/jax-vocos
Project-URL: Issues, https://github.com/flyingblackshark/jax-vocos/issues
Classifier: Development Status :: 5 - Production/Stable
Classifier: Intended Audience :: Developers
Classifier: Intended Audience :: Education
Classifier: Intended Audience :: Science/Research
Classifier: License :: OSI Approved :: MIT License
Classifier: Topic :: Scientific/Engineering :: Mathematics
Classifier: Topic :: Scientific/Engineering :: Artificial Intelligence
Classifier: Topic :: Software Development :: Libraries :: Python Modules
Classifier: Topic :: System :: Distributed Computing
Classifier: Programming Language :: Python :: 3
Requires-Python: >=3.8
Requires-Dist: jax
Requires-Dist: flax
Requires-Dist: torch
Requires-Dist: audax
Requires-Dist: requests
